dml/__init__.py
dml/encoder.py
dml/errors.py
dml/fileutils.py
dml/run.py
dml/symbols.py
dotted_ml-1.0.1.dist-info/LICENSE
dotted_ml-1.0.1.dist-info/METADATA
dotted_ml-1.0.1.dist-info/WHEEL
dotted_ml-1.0.1.dist-info/top_level.txt
dotted_ml-1.0.1.dist-info/RECORD
