Metadata-Version: 2.1
Name: dotted-ml
Version: 1.0.1
Summary: Translate text to and from DML with ease.
Home-page: https://github.com/RGBCube/dml
Author: RGBCube
License: MIT
Platform: UNKNOWN
License-File: LICENSE
